ament_cmake_uncrustify/_dummy.cpython-312-x86_64-linux-gnu.so
ros_ament_cmake_uncrustify-0.17.3.data/data/share/ament_cmake_uncrustify/local_setup.bash
ros_ament_cmake_uncrustify-0.17.3.data/data/share/ament_cmake_uncrustify/local_setup.dsv
ros_ament_cmake_uncrustify-0.17.3.data/data/share/ament_cmake_uncrustify/local_setup.sh
ros_ament_cmake_uncrustify-0.17.3.data/data/share/ament_cmake_uncrustify/local_setup.zsh
ros_ament_cmake_uncrustify-0.17.3.data/data/share/ament_cmake_uncrustify/package.dsv
ros_ament_cmake_uncrustify-0.17.3.data/data/share/ament_cmake_uncrustify/package.xml
ros_ament_cmake_uncrustify-0.17.3.data/data/share/ament_cmake_uncrustify/cmake/ament_cmake_uncrustify-extras.cmake
ros_ament_cmake_uncrustify-0.17.3.data/data/share/ament_cmake_uncrustify/cmake/ament_cmake_uncrustifyConfig-version.cmake
ros_ament_cmake_uncrustify-0.17.3.data/data/share/ament_cmake_uncrustify/cmake/ament_cmake_uncrustifyConfig.cmake
ros_ament_cmake_uncrustify-0.17.3.data/data/share/ament_cmake_uncrustify/cmake/ament_cmake_uncrustify_lint_hook.cmake
ros_ament_cmake_uncrustify-0.17.3.data/data/share/ament_cmake_uncrustify/cmake/ament_uncrustify.cmake
ros_ament_cmake_uncrustify-0.17.3.data/data/share/ament_cmake_uncrustify/environment/ament_prefix_path.dsv
ros_ament_cmake_uncrustify-0.17.3.data/data/share/ament_cmake_uncrustify/environment/ament_prefix_path.sh
ros_ament_cmake_uncrustify-0.17.3.data/data/share/ament_cmake_uncrustify/environment/path.dsv
ros_ament_cmake_uncrustify-0.17.3.data/data/share/ament_cmake_uncrustify/environment/path.sh
ros_ament_cmake_uncrustify-0.17.3.data/data/share/ament_index/resource_index/package_run_dependencies/ament_cmake_uncrustify
ros_ament_cmake_uncrustify-0.17.3.data/data/share/ament_index/resource_index/packages/ament_cmake_uncrustify
ros_ament_cmake_uncrustify-0.17.3.data/data/share/ament_index/resource_index/parent_prefix_path/ament_cmake_uncrustify
ros_ament_cmake_uncrustify-0.17.3.dist-info/METADATA
ros_ament_cmake_uncrustify-0.17.3.dist-info/WHEEL
ros_ament_cmake_uncrustify-0.17.3.dist-info/top_level.txt
ros_ament_cmake_uncrustify-0.17.3.dist-info/RECORD
