Metadata-Version: 2.4
Name: ros-ament-cmake-uncrustify
Version: 0.17.3
Summary: Wheel for the ament_cmake_uncrustify (ros-ament-cmake-uncrustify) ROS 2 package.
Dynamic: description
Dynamic: description-content-type
Dynamic: summary
